{"slug":"bloomberg-tax","name":"Bloomberg Tax","ticker":null,"isPublic":false,"entityType":"unknown","ownership":"private","parentCompany":null,"parentSlug":null,"financials":null,"financialsByYear":null,"mentionedBy":[{"slug":"intuit","name":"Intuit Inc.","ticker":"INTU","year":2025,"notes":"Leading provider of tax research, analysis and compliance tools for tax professionals with comprehensive suite for complex tax scenarios"}],"competitors":[],"notes":{"2025":[{"from":"Intuit Inc.","note":"Leading provider of tax research, analysis and compliance tools for tax professionals with comprehensive suite for complex tax scenarios"}]}}