{"slug":"buildbox","name":"Buildbox","ticker":null,"isPublic":false,"entityType":"unknown","ownership":"private","parentCompany":null,"parentSlug":null,"financials":null,"financialsByYear":null,"mentionedBy":[{"slug":"unity","name":"Unity Software Inc.","ticker":"U","year":2020,"notes":"Game development platform alternative focusing on simplified game creation."}],"competitors":[],"notes":{"2020":[{"from":"Unity Software Inc.","note":"Game development platform alternative focusing on simplified game creation."}]}}