{"slug":"cloudbees","name":"CloudBees","ticker":null,"isPublic":false,"entityType":"unknown","ownership":"private","parentCompany":null,"parentSlug":null,"financials":null,"financialsByYear":null,"mentionedBy":[{"slug":"jfrog","name":"JFrog Ltd.","ticker":"FROG","year":2024,"notes":"Enterprise CI/CD platform based on Jenkins, competing in continuous delivery and DevOps automation"},{"slug":"jfrog","name":"JFrog Ltd.","ticker":"FROG","year":2025,"notes":"Enterprise DevOps platform competitor providing continuous integration, delivery, and software supply chain management solutions that overlap with JFrog's offerings."}],"competitors":[],"notes":{"2024":[{"from":"JFrog Ltd.","note":"Enterprise CI/CD platform based on Jenkins, competing in continuous delivery and DevOps automation"}],"2025":[{"from":"JFrog Ltd.","note":"Enterprise DevOps platform competitor providing continuous integration, delivery, and software supply chain management solutions that overlap with JFrog's offerings."}]}}