{"slug":"community-brands","name":"Community Brands","ticker":null,"isPublic":false,"entityType":"unknown","ownership":"private","parentCompany":null,"parentSlug":null,"financials":null,"financialsByYear":null,"mentionedBy":[{"slug":"blackbaud","name":"Blackbaud Inc.","ticker":"BLKB","year":2015,"notes":"Enterprise software for nonprofits"},{"slug":"blackbaud","name":"Blackbaud Inc.","ticker":"BLKB","year":2024,"notes":"Enterprise competitor"}],"competitors":[],"notes":{"2015":[{"from":"Blackbaud Inc.","note":"Enterprise software for nonprofits"}],"2024":[{"from":"Blackbaud Inc.","note":"Enterprise competitor"}]}}