{"slug":"converge","name":"Converge","ticker":null,"isPublic":false,"entityType":"unknown","ownership":"private","parentCompany":null,"parentSlug":null,"financials":null,"financialsByYear":null,"mentionedBy":[{"slug":"bentley-incorporated","name":"Bentley Systems Incorporated","ticker":"BSY","year":2025,"notes":"Infrastructure software competitor listed among top competitors."}],"competitors":[],"notes":{"2025":[{"from":"Bentley Systems Incorporated","note":"Infrastructure software competitor listed among top competitors."}]}}