{"slug":"framer","name":"Framer","ticker":null,"isPublic":false,"entityType":"unknown","ownership":"private","parentCompany":null,"parentSlug":null,"financials":null,"financialsByYear":null,"mentionedBy":[{"slug":"figma","name":"Figma","ticker":"FIGM","year":2020,"notes":"Design and prototyping tool with code-based interactions"},{"slug":"figma","name":"Figma","ticker":"FIGM","year":2024,"notes":"Design tool with AI features and website publishing capabilities"},{"slug":"figma","name":"Figma","ticker":"FIGM","year":2025,"notes":"AI-powered design and website builder with strong product velocity"}],"competitors":[],"notes":{"2020":[{"from":"Figma","note":"Design and prototyping tool with code-based interactions"}],"2024":[{"from":"Figma","note":"Design tool with AI features and website publishing capabilities"}],"2025":[{"from":"Figma","note":"AI-powered design and website builder with strong product velocity"}]}}