{"slug":"google-display-video-360-dv360","name":"Google Display & Video 360 (DV360)","ticker":null,"isPublic":false,"entityType":"unknown","ownership":"private","parentCompany":null,"parentSlug":null,"financials":null,"financialsByYear":null,"mentionedBy":[{"slug":"the-trade-desk","name":"The Trade Desk","ticker":"TTD","year":2024,"notes":"Largest walled garden competitor with deep integration into Google's ecosystem, search engine, Google Ads, and Google Analytics with extensive data resources"}],"competitors":[],"notes":{"2024":[{"from":"The Trade Desk","note":"Largest walled garden competitor with deep integration into Google's ecosystem, search engine, Google Ads, and Google Analytics with extensive data resources"}]}}