{"slug":"grid-dynamics","name":"Grid Dynamics","ticker":null,"isPublic":false,"entityType":"unknown","ownership":"private","parentCompany":null,"parentSlug":null,"financials":null,"financialsByYear":null,"mentionedBy":[{"slug":"globant","name":"Globant","ticker":"GLOB","year":2025,"notes":"Digital engineering company providing technology consulting, platform and product engineering, artificial intelligence, and digital engagement services."}],"competitors":[],"notes":{"2025":[{"from":"Globant","note":"Digital engineering company providing technology consulting, platform and product engineering, artificial intelligence, and digital engagement services."}]}}