{"slug":"ibm-db2","name":"IBM DB2","ticker":null,"isPublic":false,"entityType":"product","ownership":"public","parentCompany":"IBM Corporation","parentSlug":"ibm","financials":null,"financialsByYear":null,"mentionedBy":[{"slug":"oracle","name":"Oracle Corporation","ticker":"ORCL","year":2000,"notes":"Major enterprise database competitor"},{"slug":"oracle","name":"Oracle Corporation","ticker":"ORCL","year":2005,"notes":"Main database competitor"},{"slug":"snowflake","name":"Snowflake Inc.","ticker":"SNOW","year":2015,"notes":"Enterprise data warehouse with MPP architecture"},{"slug":"snowflake","name":"Snowflake Inc.","ticker":"SNOW","year":2020,"notes":"Enterprise data warehouse with MPP and BLU technology"},{"slug":"teradata","name":"Teradata Corporation","ticker":"TDC","year":2000,"notes":"Enterprise database and data warehousing"}],"competitors":[],"notes":{"2000":[{"from":"Oracle Corporation","note":"Major enterprise database competitor"},{"from":"Teradata Corporation","note":"Enterprise database and data warehousing"}],"2005":[{"from":"Oracle Corporation","note":"Main database competitor"}],"2015":[{"from":"Snowflake Inc.","note":"Enterprise data warehouse with MPP architecture"}],"2020":[{"from":"Snowflake Inc.","note":"Enterprise data warehouse with MPP and BLU technology"}]}}