{"slug":"inception-crm","name":"Inception CRM","ticker":null,"isPublic":false,"entityType":"unknown","ownership":"private","parentCompany":null,"parentSlug":null,"financials":null,"financialsByYear":null,"mentionedBy":[{"slug":"veeva","name":"Veeva Systems Inc.","ticker":"VEEV","year":2025,"notes":"Rated as best Veeva CRM alternative by G2 for Pharma and Biotech Software needs"}],"competitors":[],"notes":{"2025":[{"from":"Veeva Systems Inc.","note":"Rated as best Veeva CRM alternative by G2 for Pharma and Biotech Software needs"}]}}