{"slug":"jd-edwards","name":"J.D. Edwards","ticker":null,"isPublic":false,"entityType":"unknown","ownership":"private","parentCompany":null,"parentSlug":null,"financials":null,"financialsByYear":null,"mentionedBy":[{"slug":"sap","name":"SAP","ticker":"SAP","year":2000,"notes":"Mid-market ERP competitor with strong manufacturing and distribution focus, later acquired by PeopleSoft then Oracle"}],"competitors":[],"notes":{"2000":[{"from":"SAP","note":"Mid-market ERP competitor with strong manufacturing and distribution focus, later acquired by PeopleSoft then Oracle"}]}}