{"slug":"körber","name":"Körber","ticker":null,"isPublic":false,"entityType":"unknown","ownership":"private","parentCompany":null,"parentSlug":null,"financials":null,"financialsByYear":null,"mentionedBy":[{"slug":"manhattan-associates","name":"Manhattan Associates Inc.","ticker":"MANH","year":2025,"notes":"Supply chain software including warehouse management systems"}],"competitors":[],"notes":{"2025":[{"from":"Manhattan Associates Inc.","note":"Supply chain software including warehouse management systems"}]}}