{"slug":"ltimindtree","name":"LTIMindtree","ticker":null,"isPublic":false,"entityType":"unknown","ownership":"private","parentCompany":null,"parentSlug":null,"financials":null,"financialsByYear":null,"mentionedBy":[{"slug":"cognizant-solutions","name":"Cognizant Technology Solutions","ticker":"CTSH","year":2024,"notes":"Combined IT services firm competing in digital transformation"}],"competitors":[],"notes":{"2024":[{"from":"Cognizant Technology Solutions","note":"Combined IT services firm competing in digital transformation"}]}}