{"slug":"nord-security","name":"Nord Security","ticker":null,"isPublic":false,"entityType":"unknown","ownership":"private","parentCompany":null,"parentSlug":null,"financials":null,"financialsByYear":null,"mentionedBy":[{"slug":"gen-digital","name":"Gen Digital","ticker":"GEN","year":2025,"notes":"Competitor in privacy and security tools with VPN and protection services"}],"competitors":[],"notes":{"2025":[{"from":"Gen Digital","note":"Competitor in privacy and security tools with VPN and protection services"}]}}