{"slug":"sketch","name":"Sketch","ticker":null,"isPublic":false,"entityType":"company","ownership":"private","parentCompany":null,"parentSlug":null,"financials":{"revenue_2024":"$50M","market_cap":null,"revenue_raw":50000000,"market_cap_raw":null},"financialsByYear":{"2020":{"revenue":"$30M","revenue_raw":30000000},"2024":{"revenue":"$50M","revenue_raw":50000000}},"mentionedBy":[{"slug":"adobe","name":"Adobe Inc.","ticker":"ADBE","year":2010,"notes":"Established in 2010 as macOS-first digital design platform for UI/UX"},{"slug":"adobe","name":"Adobe Inc.","ticker":"ADBE","year":2025,"notes":"Digital design toolkit for UI/UX designers. Still viable but Figma dominates this market segment in 2025."},{"slug":"figma","name":"Figma","ticker":"FIGM","year":2015,"notes":"Dominant Mac design tool that Figma aimed to disrupt with browser-based collaboration"},{"slug":"figma","name":"Figma","ticker":"FIGM","year":2020,"notes":"Mac design tool losing market share to Figma's collaboration features"},{"slug":"figma","name":"Figma","ticker":"FIGM","year":2024,"notes":"Mac design tool with declining market share but loyal user base"},{"slug":"figma","name":"Figma","ticker":"FIGM","year":2025,"notes":"Mac design tool with reduced market presence"}],"competitors":[],"notes":{"2010":[{"from":"Adobe Inc.","note":"Established in 2010 as macOS-first digital design platform for UI/UX"}],"2015":[{"from":"Figma","note":"Dominant Mac design tool that Figma aimed to disrupt with browser-based collaboration"}],"2020":[{"from":"Figma","note":"Mac design tool losing market share to Figma's collaboration features"}],"2024":[{"from":"Figma","note":"Mac design tool with declining market share but loyal user base"}],"2025":[{"from":"Adobe Inc.","note":"Digital design toolkit for UI/UX designers. Still viable but Figma dominates this market segment in 2025."},{"from":"Figma","note":"Mac design tool with reduced market presence"}]}}