{"slug":"stripe-connect","name":"Stripe Connect","ticker":null,"isPublic":false,"entityType":"unknown","ownership":"private","parentCompany":null,"parentSlug":null,"financials":null,"financialsByYear":null,"mentionedBy":[{"slug":"payoneer","name":"Payoneer","ticker":"PAYO","year":2025,"notes":"Developer-friendly API for marketplaces and complex payment flows, strong integration capabilities"}],"competitors":[],"notes":{"2025":[{"from":"Payoneer","note":"Developer-friendly API for marketplaces and complex payment flows, strong integration capabilities"}]}}