{"slug":"warner-bros-games","name":"Warner Bros. Games","ticker":null,"isPublic":false,"entityType":"unknown","ownership":"private","parentCompany":null,"parentSlug":null,"financials":null,"financialsByYear":null,"mentionedBy":[{"slug":"electronic-arts","name":"Electronic Arts Inc.","ticker":"EA","year":2015,"notes":"Batman Arkham series"},{"slug":"taketwo-interactive","name":"Take-Two Interactive Software, Inc.","ticker":"TTWO","year":2015,"notes":"Batman Arkham, other licensed games"}],"competitors":[],"notes":{"2015":[{"from":"Electronic Arts Inc.","note":"Batman Arkham series"},{"from":"Take-Two Interactive Software, Inc.","note":"Batman Arkham, other licensed games"}]}}