{"slug":"williamssonoma","name":"Williams-Sonoma","ticker":"WSM","isPublic":false,"entityType":"company","ownership":"public","parentCompany":null,"parentSlug":null,"financials":{"revenue_2024":"$7.7B","market_cap":"$21B","revenue_raw":7700000000,"market_cap_raw":21000000000},"financialsByYear":{"2015":{"revenue":"$5B","revenue_raw":5000000000,"market_cap":"$7B","market_cap_raw":7000000000},"2020":{"revenue":"$5.7B","revenue_raw":5700000000,"market_cap":"$9B","market_cap_raw":9000000000},"2024":{"revenue":"$7.7B","revenue_raw":7700000000,"market_cap":"$21B","market_cap_raw":21000000000}},"mentionedBy":[{"slug":"wayfair","name":"Wayfair Inc.","ticker":"W","year":2010,"notes":"Pottery Barn, West Elm brands online"},{"slug":"wayfair","name":"Wayfair Inc.","ticker":"W","year":2014,"notes":"Home brands including Pottery Barn, West Elm"},{"slug":"wayfair","name":"Wayfair Inc.","ticker":"W","year":2015,"notes":"Pottery Barn, West Elm with strong online presence"},{"slug":"wayfair","name":"Wayfair Inc.","ticker":"W","year":2020,"notes":"West Elm, Pottery Barn, 650 US stores"},{"slug":"wayfair","name":"Wayfair Inc.","ticker":"W","year":2024,"notes":"Premium home brands including West Elm, Pottery Barn"},{"slug":"wayfair","name":"Wayfair Inc.","ticker":"W","year":2025,"notes":"Premium home brands portfolio"}],"competitors":[],"notes":{"2010":[{"from":"Wayfair Inc.","note":"Pottery Barn, West Elm brands online"}],"2014":[{"from":"Wayfair Inc.","note":"Home brands including Pottery Barn, West Elm"}],"2015":[{"from":"Wayfair Inc.","note":"Pottery Barn, West Elm with strong online presence"}],"2020":[{"from":"Wayfair Inc.","note":"West Elm, Pottery Barn, 650 US stores"}],"2024":[{"from":"Wayfair Inc.","note":"Premium home brands including West Elm, Pottery Barn"}],"2025":[{"from":"Wayfair Inc.","note":"Premium home brands portfolio"}]}}