{
  "company": "Dell Technologies",
  "ticker": "DELL",
  "year": 2005,
  "search_query": "Dell competitors 2005 computer hardware",
  "search_date": "2025-12-24",
  "context": "Dell Technologies Inc. is a technology infrastructure company focused on PCs, servers, storage, and IT infrastructure solutions. Expanding into enterprise with PowerEdge servers and storage.",
  "competitors": [
    {
      "name": "Hewlett-Packard (HP)",
      "notes": "Fiercest competitor; merged with Compaq in 2002 and acquired EDS; regained PC market leadership from Dell by Q4 2006"
    },
    {
      "name": "IBM",
      "notes": "One of the oldest technology companies; known for extensive R&D and innovation; sold PC business to Lenovo in 2005"
    },
    {
      "name": "Lenovo",
      "notes": "Acquired IBM's PC business in 2005, becoming a major competitor in PC and server markets"
    },
    {
      "name": "Acer",
      "notes": "Founded 1976; operates in over 70 countries with 7,900 employees as of mid-2000s"
    },
    {
      "name": "Samsung",
      "notes": "Diversified technology competitor in PC and consumer electronics"
    },
    {
      "name": "Apple",
      "notes": "Premium PC and technology competitor"
    }
  ],
  "sources": [
    "https://en.wikipedia.org/wiki/Dell",
    "https://www.marketing91.com/dell-competitors/",
    "https://www.mbaskool.com/competitors/companies/18497-dell.html"
  ]
}
