{
  "company": "Tyler Technologies Inc.",
  "ticker": "TYL",
  "year": 2015,
  "search_query": "Tyler Technologies government software competitors 2015",
  "search_date": "2025-12-24",
  "competitors": [
    {
      "name": "SAP",
      "notes": "Enterprise ERP with public sector solutions"
    },
    {
      "name": "Oracle",
      "notes": "Enterprise software for government agencies"
    },
    {
      "name": "SunGard",
      "notes": "Public sector software before FIS acquisition"
    },
    {
      "name": "Accela",
      "notes": "Civic platform for permits, licenses, and code enforcement"
    },
    {
      "name": "New World Systems",
      "notes": "Public safety software, acquired by Tyler in 2015"
    }
  ],
  "context": "Tyler Technologies, Inc. is a government software company focused on software for local government, courts, and public safety. Expanded data and analytics for government.",
  "sources": [
    "https://craft.co/tyler-technologies/competitors"
  ]
}
